doctoc/__init__.py
doctoc/cli.py
doctoc/core.py
doctoc/markdown.py
doctoc-1.0.0.dist-info/LICENSE
doctoc-1.0.0.dist-info/METADATA
doctoc-1.0.0.dist-info/WHEEL
doctoc-1.0.0.dist-info/entry_points.txt
doctoc-1.0.0.dist-info/top_level.txt
doctoc-1.0.0.dist-info/RECORD
