Metadata-Version: 2.1
Name: doctoc
Version: 1.0.0
Summary: Generate table of contents for Markdown files
Home-page: https://github.com/ktechhub/doctoc
Author: Ktechhub
Author-email: mm@ktechhub.com
License: MIT
Keywords: markdown table of contents
Classifier: License :: OSI Approved :: MIT License
Classifier: Intended Audience :: Developers
Classifier: Programming Language :: Python :: 3.12
Classifier: Programming Language :: Python :: 3.11
Classifier: Programming Language :: Python :: 3.10
Classifier: Programming Language :: Python :: 3.9
Classifier: Programming Language :: Python :: 3.8
Classifier: Programming Language :: Python :: 3.7
Classifier: Programming Language :: Python :: 3.6
Requires-Python: >=3.6
License-File: LICENSE
Requires-Dist: click
Requires-Dist: requests
